pymodaq_plugins_kern/__init__.py
pymodaq_plugins_kern/utils.py
pymodaq_plugins_kern/daq_viewer_plugins/plugins_0D/__init__.py
pymodaq_plugins_kern/daq_viewer_plugins/plugins_0D/daq_0Dviewer_KERN_572_573_KB_DS_FKB.py
pymodaq_plugins_kern/hardware/KERN_572_573_KB_DS_FKB.py
pymodaq_plugins_kern/hardware/__init__.py
pymodaq_plugins_kern/resources/__init__.py
pymodaq_plugins_kern/resources/config_template.toml
pymodaq_plugins_kern/scanners/__init__.py
pymodaq_plugins_kern-1.0.0.dist-info/METADATA
pymodaq_plugins_kern-1.0.0.dist-info/WHEEL
pymodaq_plugins_kern-1.0.0.dist-info/entry_points.txt
pymodaq_plugins_kern-1.0.0.dist-info/licenses/LICENSE
pymodaq_plugins_kern-1.0.0.dist-info/RECORD
